thermohl/__init__.py
thermohl/default_uncertainties.yaml
thermohl/distributions.py
thermohl/rain.py
thermohl/sun.py
thermohl/thermodynamics.py
thermohl/uncertainties.py
thermohl/utils.py
thermohl/power/__init__.py
thermohl/power/convective_cooling.py
thermohl/power/power_term.py
thermohl/power/radiative_cooling.py
thermohl/power/solar_heating.py
thermohl/power/cigre/__init__.py
thermohl/power/cigre/air.py
thermohl/power/cigre/convective_cooling.py
thermohl/power/cigre/joule_heating.py
thermohl/power/cigre/radiative_cooling.py
thermohl/power/cigre/solar_heating.py
thermohl/power/ieee/__init__.py
thermohl/power/ieee/air.py
thermohl/power/ieee/convective_cooling.py
thermohl/power/ieee/joule_heating.py
thermohl/power/ieee/radiative_cooling.py
thermohl/power/ieee/solar_heating.py
thermohl/power/olla/__init__.py
thermohl/power/olla/air.py
thermohl/power/olla/convective_cooling.py
thermohl/power/olla/joule_heating.py
thermohl/power/olla/radiative_cooling.py
thermohl/power/olla/solar_heating.py
thermohl/power/rte/__init__.py
thermohl/power/rte/air.py
thermohl/power/rte/convective_cooling.py
thermohl/power/rte/joule_heating.py
thermohl/power/rte/radiative_cooling.py
thermohl/power/rte/solar_heating.py
thermohl/solver/__init__.py
thermohl/solver/base.py
thermohl/solver/slv1d.py
thermohl/solver/slv1t.py
thermohl/solver/slv3t.py
thermohl/solver/slv3t_legacy.py
thermohl-1.3.2.dist-info/licenses/LICENSE
thermohl-1.3.2.dist-info/METADATA
thermohl-1.3.2.dist-info/WHEEL
thermohl-1.3.2.dist-info/top_level.txt
thermohl-1.3.2.dist-info/RECORD
