Metadata-Version: 2.4
Name: thermohl
Version: 1.3.2
Summary: Calculations relative to temperature and ampacity in overhead conductors.
License-Expression: MPL-2.0
Project-URL: Homepage, https://github.com/phlowers/thermohl
Project-URL: Documentation, https://phlowers.readthedocs.io/projects/thermohl
Project-URL: Issues, https://github.com/phlowers/thermohl/issues
Classifier: Intended Audience :: Science/Research
Classifier: Intended Audience :: Developers
Classifier: Natural Language :: English
Classifier: Programming Language :: Python :: 3 :: Only
Classifier: Programming Language :: Python :: 3.9
Classifier: Programming Language :: Python :: 3.10
Classifier: Programming Language :: Python :: 3.11
Classifier: Programming Language :: Python :: 3.12
Classifier: Operating System :: OS Independent
Requires-Python: <3.13,>=3.9
License-File: LICENSE
Requires-Dist: numpy>=1.26.0
Requires-Dist: pandas>=2.1.2
Requires-Dist: scipy>=1.13.1
Requires-Dist: pyyaml>=6.0.1
Provides-Extra: test
Requires-Dist: pytest>=7.2.2; extra == "test"
Requires-Dist: pytest-cov>=6.0.0; extra == "test"
Requires-Dist: pylint>=3.3.1; extra == "test"
Provides-Extra: lint
Requires-Dist: black>=25.1.0; extra == "lint"
Requires-Dist: mypy>=1.13.0; extra == "lint"
Requires-Dist: ruff>=0.8.0; extra == "lint"
Provides-Extra: dev
Requires-Dist: thermohl[lint,test]; extra == "dev"
Provides-Extra: docs
Requires-Dist: mkdocs>=1.6.1; extra == "docs"
Requires-Dist: mkdocs-bibtex; extra == "docs"
Requires-Dist: mkdocs-jupyter; extra == "docs"
Requires-Dist: mkdocs-material>=9.6.9; extra == "docs"
Requires-Dist: mkdocstrings[python]>=0.29.0; extra == "docs"
Requires-Dist: markdown_extensions>=0.0.1; extra == "docs"
Requires-Dist: markdown-include>=0.8.1; extra == "docs"
Requires-Dist: mkdocs-markdownextradata-plugin>=0.2.6; extra == "docs"
Requires-Dist: thermohl[lint]; extra == "docs"
Dynamic: license-file
